{
    "schemaVersion": 1,
    "id": "nether-right",
    "version": "${version}",

    "name": "Anvil Recipe",
    "description": "Adds anvil as a crafting type for recipes!",
    "authors": [
        "Nick Kennedy"
    ],
    "contact": {
        "homepage": "http://minecraft.odd.dev/mods/AnvilRecipe",
        "sources": "https://github.com/approved/AnvilRecipe"
    },

    "license": "CC0-1.0",
    "icon": "assets/anvilrecipe/icon.png",

    "environment": "*",
    "entrypoints": {
        "main": ["dev.odd.anvilrecipe.recipe.AnvilRecipeLoader"]
    },
    "mixins": [
        "anvilrecipe.mixins.json"
    ],

    "depends": {
        "fabricloader": ">=0.7.8",
        "fabric": "*"
    },
    "suggests": {
        "flamingo": "*"
    }
}